DLT/Exceptions.py
DLT/__init__.py
DLT/dlt.py
DLT/splitter.py
DLT/utils.py
Dynamic_Learning_Technique-0.3.dist-info/LICENSE
Dynamic_Learning_Technique-0.3.dist-info/METADATA
Dynamic_Learning_Technique-0.3.dist-info/WHEEL
Dynamic_Learning_Technique-0.3.dist-info/top_level.txt
Dynamic_Learning_Technique-0.3.dist-info/RECORD
