Metadata-Version: 2.1
Name: Dynamic-Learning-Technique
Version: 0.3
Summary: Dynamic learning technique allows the user to train a model in batch wise manner
Home-page: https://github.com/TONYSTARK-EDITH/Dynamic-Learning-Technique
Author: Tony Stark
Author-email: manthirajak@gmail.com
License: UNKNOWN
Keywords: DLT,Dynamic Learning Technique,python
Platform: UNKNOWN
Classifier: Programming Language :: Python :: 3
Classifier: License :: OSI Approved :: MIT License
Classifier: Operating System :: OS Independent
Requires-Python: >=3.0
License-File: LICENSE
Requires-Dist: numpy
Requires-Dist: asyncio
Requires-Dist: scikit-learn
